base_page/__init__.py
base_page/base_page.py
core_page-0.1.1.dist-info/LICENSE
core_page-0.1.1.dist-info/METADATA
core_page-0.1.1.dist-info/WHEEL
core_page-0.1.1.dist-info/top_level.txt
core_page-0.1.1.dist-info/RECORD
