Metadata-Version: 2.1
Name: core-page
Version: 0.1.1
Summary: Утилита для расширенного взаимодействия с любым веб-сайтом и его страницами
Author: dmitry
Author-email: dmitryvshivtsev@gmail.com
License-File: LICENSE
Requires-Dist: pytest ==7.4.0
Requires-Dist: selenium ==4.10.0
